antflow/__init__.py
antflow/_version.py
antflow/context.py
antflow/exceptions.py
antflow/executor.py
antflow/pipeline.py
antflow/tracker.py
antflow/types.py
antflow/utils.py
antflow/display/__init__.py
antflow/display/base.py
antflow/display/compact.py
antflow/display/detailed.py
antflow/display/full.py
antflow/display/progress.py
antflow-0.7.2.dist-info/licenses/LICENSE
antflow-0.7.2.dist-info/METADATA
antflow-0.7.2.dist-info/WHEEL
antflow-0.7.2.dist-info/top_level.txt
antflow-0.7.2.dist-info/RECORD
