Metadata-Version: 2.4
Name: antflow
Version: 0.7.2
Summary: AntFlow: Async execution library with concurrent.futures-style API and advanced pipelines
Author-email: Rodolfo Nobrega <rodolfo@example.com>
License: MIT
Project-URL: Homepage, https://github.com/rodolfonobrega/antflow
Project-URL: Documentation, https://rodolfonobrega.github.io/antflow
Project-URL: Repository, https://github.com/rodolfonobrega/antflow
Project-URL: Issues, https://github.com/rodolfonobrega/antflow/issues
Keywords: antflow,async,asyncio,pipeline,concurrent,futures,executor,worker-pool
Classifier: Development Status :: 4 - Beta
Classifier: Intended Audience :: Developers
Classifier: License :: OSI Approved :: MIT License
Classifier: Programming Language :: Python :: 3
Classifier: Programming Language :: Python :: 3.9
Classifier: Programming Language :: Python :: 3.10
Classifier: Programming Language :: Python :: 3.11
Classifier: Programming Language :: Python :: 3.12
Classifier: Programming Language :: Python :: 3.13
Classifier: Topic :: Software Development :: Libraries :: Python Modules
Classifier: Framework :: AsyncIO
Requires-Python: >=3.9
License-File: LICENSE
Requires-Dist: tenacity>=8.0.0
Requires-Dist: rich>=13.0.0
Requires-Dist: taskgroup>=0.0.0a4; python_version < "3.11"
Provides-Extra: dev
Requires-Dist: pytest>=7.0; extra == "dev"
Requires-Dist: pytest-asyncio>=0.21.0; extra == "dev"
Requires-Dist: mypy>=1.0; extra == "dev"
Requires-Dist: ruff>=0.1.0; extra == "dev"
Provides-Extra: docs
Requires-Dist: mkdocs>=1.5.0; extra == "docs"
Requires-Dist: mkdocs-material>=9.0.0; extra == "docs"
Requires-Dist: mkdocstrings[python]>=0.24.0; extra == "docs"
Requires-Dist: mkdocs-autorefs>=0.6.0; extra == "docs"
Dynamic: license-file
